feedcommas/__init__.py
feedcommas/_version.py
feedcommas/actions.py
feedcommas/app.py
feedcommas/client.py
feedcommas/config.py
feedcommas/content.py
feedcommas/dialog.py
feedcommas/gui_utils.py
feedcommas/key.py
feedcommas/locale.py
feedcommas/log.py
feedcommas/model.py
feedcommas/utils.py
feedcommas/widgets.py
feedcommas-0.3.0.dist-info/DESCRIPTION.rst
feedcommas-0.3.0.dist-info/METADATA
feedcommas-0.3.0.dist-info/RECORD
feedcommas-0.3.0.dist-info/WHEEL
feedcommas-0.3.0.dist-info/entry_points.txt
feedcommas-0.3.0.dist-info/metadata.json
feedcommas-0.3.0.dist-info/top_level.txt
