Metadata-Version: 2.0
Name: feedcommas
Version: 0.3.0
Summary: CommaFeed commandline client
Home-page: https://gitlab.com/mgoral/feed-commas
Author: Michał Góral
Author-email: dev@mgoral.org
License: GPLv3+
Platform: linux
Classifier: Development Status :: 4 - Beta
Classifier: Environment :: Console
Classifier: Environment :: Console :: Curses
Classifier: Intended Audience :: End Users/Desktop
Classifier: License :: OSI Approved :: GNU General Public License v3 or later (GPLv3+)
Classifier: Natural Language :: English
Classifier: Operating System :: POSIX
Classifier: Programming Language :: Python :: 3 :: Only
Classifier: Programming Language :: Python :: 3.4
Classifier: Programming Language :: Python :: 3.5
Classifier: Programming Language :: Python :: 3.6
Classifier: Topic :: Software Development :: Libraries
Classifier: Topic :: Utilities
Requires-Dist: beautifulsoup4 (>=4.5.3)
Requires-Dist: mgcomm (>=0.1.0)
Requires-Dist: requests (==2.13.0)
Requires-Dist: sqlalchemy (>=1.1.6)
Requires-Dist: urwid (==1.3.1)
